control.v
module control
(
	instruction,
	MemRW,
	regWrite,
	memReg,
	regDst,
	ALUSrc,
	alu_control,
	alu_zero,
	pc_control
);


        input[31:0] instruction;
	input alu_zero; 

        output MemRW;
	output regWrite;
	output memReg;
	output regDst;
	output ALUSrc;
	output[3:0] alu_control;
	output[2:0] pc_control;
	
	//reg
	reg MemRW;
	reg regWrite;
	reg memReg;
	reg regDst;
	reg ALUSrc;
	reg [3:0] alu_control;
	reg [2:0] pc_control;
    
   
	reg [25:0] address;
	reg [5:0] funct;
	reg [15:0] immediate;
    	reg [4:0] rs;
    	reg [4:0] rt;
    	reg [4:0] rd;
    	reg [4:0] shamt;
    	reg [2:0] type;
	
	wire [5:0] op;
	
	assign op = instruction[31:26]; // Set the opcode
	
	always @(*)
	begin		
		if (op == 6'h0) begin // R format
			address	  = 26'b00000000000000000000000000;
			immediate = 16'b0000000000000000;
			rs = instruction[25:21];
			rt = instruction[20:16];
			rd = instruction[15:11];
			shamt = instruction[10:6];
			type  = 3'b001;
			funct = instruction[5:0];
		end 

		else if (op == 6'h3F || op == 6'h02) begin // J format
			address = instruction[25:0];
			immediate = 16'b0000000000000000;
			rs = 5'b00000;
			rt = 5'b00000;
			rd = 5'b00000;
			shamt= 5'b00000;
			type = 3'b100;
			funct= 6'b000000;
		end 

		else begin // I format
			address = 26'b00000000000000000000000000;
			immediate = instruction[15:0];
			rs = instruction[25:21];
			rt = instruction[20:16];
			rd = 5'b00000;
			shamt= instruction[10:6];
			type = 3'b010;
			funct= instruction[5:0];
		end
	
	
	//alu control
		
		if ((op == 6'h0 && funct == 6'h13) || op == 6'h04) begin // OR & ORI
			alu_control = 4'b0001;
		end else if (((op == 6'h0) && (funct == 6'h20)) || (op == 6'h08)) begin // ADD & ADDI
			alu_control = 4'b0010; 
		end else if ((op == 6'h0 && funct == 6'h14)) begin // XOR
			alu_control = 4'b0011;
		end else if ((op == 6'h0 && funct == 6'h22) || op == 6'h02) begin // SUB & SUBI - unsigned
			alu_control = 4'b0110;
		end else if (op == 6'h05) begin // SLL
			alu_control = 4'b1000;
		end else if (op == 6'h06) begin // SRL
			alu_control = 4'b1001;
		end else if (op == 6'h09 || op == 6'h0A || op == 6'h0B) begin // SUB - signed - AND bne, beq, blt
			alu_control = 4'b0110;
		end else if (op == 6'h2b || op == 6'h23) begin // LW, SW
			alu_control = 4'b0010;
       		 end else begin
			alu_control = 4'b1111;
		end		

		//MemWrite
		if (op == 6'h2b) begin // store word
			MemRW = 1'b1;
		end 
		else begin // no write
			MemRW = 1'b0;
		end
		
		//RegWrite
		if (op == 6'h0 || op == 6'h23 || op == 6'h08 ) begin // R, lw, I
			regWrite = 1;
		end 
		else begin // Otherwise 1
			regWrite = 0;
		end
		
		
		//MemtoReg
		if (op == 6'h23) begin //load word
			memReg = 1;
		end
		else begin
			memReg = 0;
		end
		
		
		//RegDst
		if (op == 6'h0) begin // R format
			regDst = 1;
		end 
		else begin // I format or other
			regDst = 0;
		end
		
		//ALUSrc
		if (op == 6'h23 || op == 6'h2b || op == 6'h08) begin // R format or brach
			ALUSrc = 1;
		end else begin // I or J format
			ALUSrc = 0;
		end
		
		//pc_control
		if (op == 6'h02) begin // jmp
			pc_control = 3'b001;
		end else if (op == 6'h04 && alu_zero == 1) begin // beq
				pc_control = 3'b011;	
		end else if (op == 6'h0B && alu_zero == 0) begin // bne
				pc_control = 3'b011;
		end else if (op == 6'h09 && alu_zero == 0) begin //blt
				pc_control = 3'b011;
		end else if (op == 6'h3F) begin //halt
				pc_control = 3'b111;
        	end else begin 
			pc_control = 3'b000;
		end
		
		
	end
	
 endmodule

control_tb.v
`include "control.v"

module control_tb();

reg[31:0] instruction;
reg alu_zero; 

wire MemRW;
wire regWrite;
wire memReg;
wire regDst;
wire ALUSrc;
wire[3:0] alu_control;
wire[2:0] pc_control;

control Control (.instruction(instruction),
	.MemRW(MemRW),
	.regWrite(regWrite),
	.memReg(memReg),
	.regDst(regDst),
	.ALUSrc(ALUSrc),
	.alu_control(alu_control),
	.alu_zero(alu_zero),
	.pc_control(pc_control)
	);

initial begin                        //Simulation start
	$dumpfile("control.vcd");   //vcf file creation for GTKWave 
	$dumpvars(0, control_tb);
    
    	alu_zero = 0;
	instruction = 32'h00000000;                //Inputs initialization

	#10;
    	alu_zero = 1;
	instruction = 32'h21080002; //addi $t0, $t0, 2 

	#10;
    	alu_zero = 0;
	instruction =  32'h214A0002; //addi $t2, $t2, 2  214A0002

	#10;
    	alu_zero = 1;
	instruction = 32'h010A4020; //add $t0, $t0, $t2 

	#10;
    	alu_zero = 0;
	instruction = 32'h21290001; //addi $t1, $t1, 1 

	#10;
    	alu_zero = 0;
	instruction =  32'hAD090000; //sw $t0, 0($t1)
	
	#10;
    	alu_zero = 0;
	instruction = 32'h8D490000; //lw $t2, 0($t1); //sw $t0, 0($t1)

	#10;
    	alu_zero = 0;
	instruction = 32'h01094022; //loop: sub $t0, $t0, $t1

	#10;
    	alu_zero = 0;
	instruction = 32'h11090048; //beq $t0, $t1, end

	#10;
    	alu_zero = 0;
	instruction = 32'h08000007; //j loop- opcode + the lower 26 bits of address 

	#10;
    	alu_zero = 0;
	instruction = 32'hFCFFFFFF;

  	#10;
	$finish;                 //Simulation end

end

endmodule

control.vcd
$date
	Mon Oct 29 00:09:45 2018
$end
$version
	Icarus Verilog
$end
$timescale
	1s
$end
$scope module control_tb $end
$var wire 1 ! regWrite $end
$var wire 1 " regDst $end
$var wire 3 # pc_control [2:0] $end
$var wire 1 $ memReg $end
$var wire 4 % alu_control [3:0] $end
$var wire 1 & MemRW $end
$var wire 1 ' ALUSrc $end
$var reg 1 ( alu_zero $end
$var reg 32 ) instruction [31:0] $end
$scope module Control $end
$var wire 1 ( alu_zero $end
$var wire 32 * instruction [31:0] $end
$var wire 6 + op [5:0] $end
$var reg 1 ' ALUSrc $end
$var reg 1 & MemRW $end
$var reg 26 , address [25:0] $end
$var reg 4 - alu_control [3:0] $end
$var reg 6 . funct [5:0] $end
$var reg 16 / immediate [15:0] $end
$var reg 1 $ memReg $end
$var reg 3 0 pc_control [2:0] $end
$var reg 5 1 rd [4:0] $end
$var reg 1 " regDst $end
$var reg 1 ! regWrite $end
$var reg 5 2 rs [4:0] $end
$var reg 5 3 rt [4:0] $end
$var reg 5 4 shamt [4:0] $end
$var reg 3 5 type [2:0] $end
$upscope $end
$upscope $end
$enddefinitions $end
#0
$dumpvars
b1 5
b0 4
b0 3
b0 2
b0 1
b0 0
b0 /
b0 .
b1111 -
b0 ,
b0 +
b0 *
b0 )
0(
0'
0&
b1111 %
0$
b0 #
1"
1!
$end
#10
1'
0"
b10 %
b10 -
b10 5
b10 /
b1000 +
b10 .
b1000 3
b1000 2
b100001000010000000000000000010 )
b100001000010000000000000000010 *
1(
#20
b1010 3
b1010 2
b100001010010100000000000000010 )
b100001010010100000000000000010 *
0(
#30
0'
1"
b1 5
b1000 1
b0 +
b100000 .
b1000 2
b0 /
b1000010100100000000100000 )
b1000010100100000000100000 *
1(
#40
1'
0"
b10 5
b1 /
b1000 +
b10 %
b10 -
b1 .
b0 1
b1001 3
b1001 2
b100001001010010000000000000001 )
b100001001010010000000000000001 *
0(
#50
0!
1&
b0 .
b1000 2
b0 /
b101011 +
b10101101000010010000000000000000 )
b10101101000010010000000000000000 *
#60
1$
1!
0&
b1010 2
b100011 +
b10001101010010010000000000000000 )
b10001101010010010000000000000000 *
#70
0'
1"
0$
b110 %
b110 -
b100010 .
b1 5
b1000 1
b1000 2
b0 +
b1000010010100000000100010 )
b1000010010100000000100010 *
#80
0"
0!
b1 %
b1 -
b1000 .
b10 5
b1 4
b0 1
b1001000 /
b100 +
b10001000010010000000001001000 )
b10001000010010000000001001000 *
#90
b1 #
b1 0
b110 %
b110 -
b0 .
b100 5
b0 4
b0 3
b0 2
b0 /
b111 ,
b10 +
b1000000000000000000000000111 )
b1000000000000000000000000111 *
#100
b111 #
b111 0
b1111 %
b1111 -
b111111111111111111111111 ,
b111111 +
b11111100111111111111111111111111 )
b11111100111111111111111111111111 *
